alibabacloud_docmind_api20220729/__init__.py
alibabacloud_docmind_api20220729/client.py
alibabacloud_docmind_api20220729/models.py
alibabacloud_docmind_api20220729_py2-1.0.0.dist-info/LICENSE
alibabacloud_docmind_api20220729_py2-1.0.0.dist-info/METADATA
alibabacloud_docmind_api20220729_py2-1.0.0.dist-info/WHEEL
alibabacloud_docmind_api20220729_py2-1.0.0.dist-info/top_level.txt
alibabacloud_docmind_api20220729_py2-1.0.0.dist-info/RECORD
